<?xml version="1.0" encoding="UTF-8"?>
<ParamSection>
	<ParamSectHeader>
		<AutoHotspots>false</AutoHotspots>
		<StatBits>
			<STBit_FixSize/>
		</StatBits>
		<WDLeftFrame>0</WDLeftFrame>
		<WDRightFrame>0</WDRightFrame>
		<WDTopFrame>0</WDTopFrame>
		<WDBotFrame>0</WDBotFrame>
		<LayFlags>65535</LayFlags>
		<WDMirrorThickness>0</WDMirrorThickness>
		<WDWallInset>0</WDWallInset>
	</ParamSectHeader>
	<Parameters SectVersion="22" SectionFlags="0" SubIdent="0">
		<Length Name="A">
			<Description><![CDATA["Размер 1"]]></Description>
			<Fix/>
			<Flags>
				<ParFlg_Hidden/>
			</Flags>
			<Value>1</Value>
		</Length>
		<Length Name="B">
			<Description><![CDATA["Размер 2"]]></Description>
			<Fix/>
			<Flags>
				<ParFlg_Hidden/>
			</Flags>
			<Value>1</Value>
		</Length>
		<Length Name="ZZYZX">
			<Description><![CDATA["Высота"]]></Description>
			<Fix/>
			<Flags>
				<ParFlg_Hidden/>
			</Flags>
			<Value>1</Value>
		</Length>
		<Boolean Name="AC_show2DHotspotsIn3D">
			<Description><![CDATA["Показ Узловых 2D Точек в 3D"]]></Description>
			<Fix/>
			<Flags>
				<ParFlg_Hidden/>
			</Flags>
			<Value>1</Value>
		</Boolean>
		<Length Name="ac_bottomlevel">
			<Description><![CDATA["Отметка Низа"]]></Description>
			<Fix/>
			<Flags>
				<ParFlg_Hidden/>
			</Flags>
			<Value>1</Value>
		</Length>
		<Length Name="ac_toplevel">
			<Description><![CDATA["Отметка Верха"]]></Description>
			<Fix/>
			<Flags>
				<ParFlg_Hidden/>
			</Flags>
			<Value>0</Value>
		</Length>
		<String Name="concrete_class">
			<Description><![CDATA[""]]></Description>
			<Value><![CDATA["В25"]]></Value>
		</String>
		<String Name="class">
			<Description><![CDATA[""]]></Description>
			<Value><![CDATA["A-I(A240)"]]></Value>
		</String>
		<Length Name="diam_arm">
			<Description><![CDATA[""]]></Description>
			<Value>0.006</Value>
		</Length>
		<String Name="stres_state">
			<Description><![CDATA[""]]></Description>
			<Value><![CDATA[""]]></Value>
		</String>
		<RealNum Name="alpha">
			<Description><![CDATA[""]]></Description>
			<Value>1</Value>
		</RealNum>
		<RealNum Name="kisp">
			<Description><![CDATA[""]]></Description>
			<Value>1</Value>
		</RealNum>
		<RealNum Name="us">
			<Description><![CDATA[""]]></Description>
			<Value>1</Value>
		</RealNum>
		<RealNum Name="n1">
			<Description><![CDATA[""]]></Description>
			<Value>1</Value>
		</RealNum>
		<RealNum Name="n2">
			<Description><![CDATA[""]]></Description>
			<Value>1</Value>
		</RealNum>
		<Length Name="l_nahl_raw">
			<Description><![CDATA[""]]></Description>
			<Value>1.51764705882353</Value>
		</Length>
		<Length Name="l_nahl_round">
			<Description><![CDATA[""]]></Description>
			<Value>0.76</Value>
		</Length>
	</Parameters>
</ParamSection>
